IndicoIo-1.2.0.dist-info/DESCRIPTION.rst
IndicoIo-1.2.0.dist-info/METADATA
IndicoIo-1.2.0.dist-info/RECORD
IndicoIo-1.2.0.dist-info/WHEEL
IndicoIo-1.2.0.dist-info/metadata.json
IndicoIo-1.2.0.dist-info/top_level.txt
indicoio/__init__.py
indicoio/config.py
indicoio/custom/__init__.py
indicoio/custom/custom.py
indicoio/docx/__init__.py
indicoio/docx/docx_extraction.py
indicoio/image/__init__.py
indicoio/image/content_filtering.py
indicoio/image/facial_features.py
indicoio/image/facial_localization.py
indicoio/image/fer.py
indicoio/image/image_features.py
indicoio/image/image_recognition.py
indicoio/multi/__init__.py
indicoio/multi/analyze_image.py
indicoio/multi/analyze_text.py
indicoio/multi/utils.py
indicoio/pdf/__init__.py
indicoio/pdf/pdf_extraction.py
indicoio/text/__init__.py
indicoio/text/emotion.py
indicoio/text/keywords.py
indicoio/text/language.py
indicoio/text/organizations.py
indicoio/text/people.py
indicoio/text/personality.py
indicoio/text/personas.py
indicoio/text/places.py
indicoio/text/political.py
indicoio/text/relevance.py
indicoio/text/sentiment.py
indicoio/text/sentiment_hq.py
indicoio/text/summarization.py
indicoio/text/text_features.py
indicoio/text/text_tags.py
indicoio/utils/__init__.py
indicoio/utils/api.py
indicoio/utils/decorators.py
indicoio/utils/docx.py
indicoio/utils/encoder.py
indicoio/utils/errors.py
indicoio/utils/pdf.py
indicoio/utils/preprocessing.py
tests/__init__.py
