Metadata-Version: 2.0
Name: IndicoIo
Version: 1.2.0
Summary: A Python Wrapper for indico. Use pre-built state of the art machine learning algorithms with a single line of code.
Home-page: https://github.com/IndicoDataSolutions/indicoio-python
Author: Alec Radford, Slater Victoroff, Aidan McLaughlin, Madison May, Anne Carlson
Author-email: engineering@indico.io
License: MIT License (See LICENSE)
Platform: UNKNOWN
Classifier: Development Status :: 5 - Production/Stable
Classifier: Intended Audience :: Developers
Classifier: Intended Audience :: Science/Research
Classifier: License :: OSI Approved :: MIT License
Classifier: Natural Language :: English
Classifier: Operating System :: OS Independent
Classifier: Programming Language :: Python
Classifier: Topic :: Scientific/Engineering
Classifier: Topic :: Scientific/Engineering :: Image Recognition
Classifier: Topic :: Scientific/Engineering :: Information Analysis
Classifier: Topic :: Software Development
Classifier: Topic :: Software Development :: Libraries :: Python Modules
Requires-Dist: requests (>=1.2.3)
Requires-Dist: six (>=1.3.0)
Requires-Dist: pillow (>=2.8.1)
Requires-Dist: msgpack (==0.5.6)
Requires-Dist: numpy (>=1.14.1)
Requires-Dist: msgpack-numpy (==0.4.1)
Requires-Dist: futures (>=3.0.0)
